dbrx_api/__init__.py
dbrx_api/errors.py
dbrx_api/main.py
dbrx_api/routes_recipient.py
dbrx_api/routes_share.py
dbrx_api/schemas.py
dbrx_api/settings.py
dbrx_api/dbrx_auth/__init__.py
dbrx_api/dbrx_auth/token_gen.py
dbrx_api/dltshr/recipient.py
dbrx_api/dltshr/share.py
deltashare_api-0.1.1.dist-info/METADATA
deltashare_api-0.1.1.dist-info/WHEEL
deltashare_api-0.1.1.dist-info/top_level.txt
deltashare_api-0.1.1.dist-info/RECORD
