Metadata-Version: 2.4
Name: deltashare_api
Version: 0.1.1
Summary: This is a Python client library for the DeltaShare API.
Author-email: Nitin Keshav <nitinkeshav.bolla@jll.com>
License: MIT
Keywords: one,two
Classifier: Programming Language :: Python :: 3
Requires-Python: >=3.12
Requires-Dist: fastapi
Requires-Dist: pydantic
Requires-Dist: pydantic_settings
Requires-Dist: dotenv
Requires-Dist: typing-extensions
Provides-Extra: dbrx
Requires-Dist: databricks-sdk; extra == "dbrx"
Provides-Extra: api
Requires-Dist: uvicorn; extra == "api"
Provides-Extra: azure
Requires-Dist: azure-storage-blob; extra == "azure"
Requires-Dist: azure-identity; extra == "azure"
Provides-Extra: test
Requires-Dist: pytest; extra == "test"
Requires-Dist: pytest-cov; extra == "test"
Provides-Extra: release
Requires-Dist: build; extra == "release"
Requires-Dist: twine; extra == "release"
Provides-Extra: static-code-qa
Requires-Dist: pre-commit; extra == "static-code-qa"
Requires-Dist: pylint; extra == "static-code-qa"
Requires-Dist: black; extra == "static-code-qa"
Requires-Dist: isort; extra == "static-code-qa"
Requires-Dist: flake8; extra == "static-code-qa"
Requires-Dist: flake8-docstrings; extra == "static-code-qa"
Requires-Dist: Flake8-pyproject; extra == "static-code-qa"
Requires-Dist: radon; extra == "static-code-qa"
Requires-Dist: mypy; extra == "static-code-qa"
Requires-Dist: types-requests; extra == "static-code-qa"
Provides-Extra: dev
Requires-Dist: deltashare_api[api,dbrx,release,static-code-qa,test]; extra == "dev"
